[
    {
        "candidate": {
            "name": "Elijah Brown",
            "email": "Email",
            "matched_skills": [
                "python",
                "machine learning",
                "deep learning"
            ],
            "missing_skills": [],
            "fit_score": "100%"
        },
        "email": "Subject: Update on Your Application for Data Scientist Role\n\nDear Elijah Brown,\n\nWe are pleased to inform you that your application for the Data Scientist position has been shortlisted. Our team has thoroughly reviewed your profile and is impressed with your exceptional fit score of 100%.\n\nWe would like to invite you to the next stage of the recruitment process, where you will have the opportunity to discuss your skills and experience in more detail. Your matched skills in Python, Machine Learning, and Deep Learning align well with the requirements of this role.\n\nA member of our team will be in touch with you shortly to schedule an interview. We look forward to learning more about your qualifications and experience.\n\nThank you for your interest in this position, and we wish you the best of luck in the next stage of the process.\n\nBest regards,\n\n[Your Name]\nHR Assistant",
        "interview_schedule": {
            "candidate_name": "Elijah Brown",
            "interview_date": "2026-03-16",
            "time_slot": "10:00 AM - 11:00 AM",
            "mode": "Offline",
            "meeting_link": "",
            "hr_contact": "John Doe, HR Manager"
        }
    },
    {
        "candidate": {
            "name": "Alexander Taylor",
            "email": "ataylor@email.com",
            "matched_skills": [
                "python",
                "machine learning"
            ],
            "missing_skills": [
                "deep learning"
            ],
            "fit_score": "71%"
        },
        "email": "Subject: Update on Your Application for Data Scientist Position\n\nDear Alexander Taylor,\n\nWe are pleased to inform you that your application for the Data Scientist position at our organization has been shortlisted. Your skills and experience have been carefully evaluated, and we are interested in moving forward with your candidacy.\n\nAs part of our next steps, we would like to invite you to an interview to further discuss your qualifications. Please note that this is a competitive process, and we will be in touch soon to schedule a convenient time for the interview.\n\nThank you for your interest in our organization, and we look forward to speaking with you soon.\n\nBest regards,\n[Your Name]\nHR Assistant",
        "interview_schedule": {
            "candidate_name": "Alexander Taylor",
            "interview_date": "2026-03-16",
            "time_slot": "10:00 AM - 11:00 AM",
            "mode": "Online",
            "meeting_link": "https://example.com/meeting/12345",
            "hr_contact": "John Doe, HR Manager"
        }
    },
    {
        "candidate": {
            "name": "Chloe Martinez",
            "email": "Email",
            "matched_skills": [
                "python",
                "machine learning"
            ],
            "missing_skills": [
                "deep learning"
            ],
            "fit_score": "71%"
        },
        "email": "Subject: Update on Your Application for Data Scientist Role\n\nDear Chloe Martinez,\n\nWe are pleased to inform you that your application for the Data Scientist position has been shortlisted for further consideration. Our review of your qualifications and experience has shown a strong alignment with the requirements of the role.\n\nWe will be in touch soon to discuss the next steps in our recruitment process. Please note that the details of the interview and assessment will be shared with you in due course.\n\nThank you for your interest in joining our team. We look forward to speaking with you soon.\n\nBest regards,\n[Your Name]\nHR Assistant",
        "interview_schedule": {
            "candidate_name": "Chloe Martinez",
            "interview_date": "2026-03-16",
            "time_slot": "10:00 AM - 11:00 AM",
            "mode": "Offline",
            "meeting_link": "",
            "hr_contact": "John Doe, [johndoe@example.com](mailto:johndoe@example.com)"
        }
    }
]